problemsolvr/__init__.py
problemsolvr/a_star.py
problemsolvr/bfs.py
problemsolvr/dfs.py
problemsolvr/greedy.py
problemsolvr/helpers.py
problemsolvr/problem_solver.py
problemsolvr/ucs.py
problemsolvr-1.0.0.dist-info/METADATA
problemsolvr-1.0.0.dist-info/WHEEL
problemsolvr-1.0.0.dist-info/top_level.txt
problemsolvr-1.0.0.dist-info/RECORD
