Metadata-Version: 2.1
Name: problemsolvr
Version: 1.0.0
Summary: An easy-to-use Python library for solving graph problems using classic search algorithms like BFS, DFS, A*, and Greedy with visualization support.
Home-page: https://github.com/yourusername/problemsolvr
Author: Zain ul Abideen
Author-email: zainthenpc03@gmail.com
Classifier: Development Status :: 4 - Beta
Classifier: Intended Audience :: Developers
Classifier: Programming Language :: Python :: 3
Classifier: License :: OSI Approved :: MIT License
Classifier: Operating System :: OS Independent
Classifier: Topic :: Software Development :: Libraries :: Python Modules
Requires-Python: >=3.6
Requires-Dist: matplotlib
Requires-Dist: networkx
